{
    "name": "\/api\/2\/album",
    "locator": "api-v2:\/api\/2\/album",
    "spec": "\/spec\/api-v2\/api\/2\/album\/route.json",
    "regex": "#\/api\/2\/album#",
    "wildcards": {},
    "endpoints": {
        "POST": {
            "method": "POST",
            "spec": "\/spec\/api-v2\/api\/2\/album\/POST.json",
            "description": "Creates an album.",
            "parameters": {
                "name": {
                    "name": "name",
                    "regex": "\/\\w+\/",
                    "description": "",
                    "isRequired": true
                }
            }
        }
    }
}